safemodels/__init__.py
safemodels/check.py
safemodels/cosign.py
safemodels/hash.py
safemodels/model.py
safemodels/patch/__init__.py
safemodels/patch/huggingface_hub.py
safemodels/patch/safetensors.py
safemodels/repo.py
safemodels/utils/safetensors.py
safemodels-0.2.0.dist-info/METADATA
safemodels-0.2.0.dist-info/WHEEL
safemodels-0.2.0.dist-info/RECORD
