Metadata-Version: 2.1
Name: safemodels
Version: 0.2.0
Summary: safetensors with model weight hashing
License: MIT
Author: Yasyf Mohamedali
Author-email: yasyfm@gmail.com
Requires-Python: >=3.9.15,<4.0.0
Classifier: License :: OSI Approved :: MIT License
Classifier: Programming Language :: Python :: 3
Classifier: Programming Language :: Python :: 3.10
Classifier: Programming Language :: Python :: 3.11
Requires-Dist: huggingface-hub (>=0.16.4,<0.17.0)
Requires-Dist: numpy (>=1.25.1,<2.0.0)
Requires-Dist: pydantic (>=2.0.2,<3.0.0)
Requires-Dist: pyyaml (>=6.0,<7.0)
Requires-Dist: safetensors (>=0.3.1,<0.4.0)
Requires-Dist: torch (>=2.0.1,<3.0.0)
